<?xml version="1.0" encoding="UTF-8"?>
<beans xmlns="http://www.springframework.org/schema/beans"
       xmlns:xsi="http://www.w3.org/2001/XMLSchema-instance"
       xsi:schemaLocation="http://www.springframework.org/schema/beans
http://www.springframework.org/schema/beans/spring-beans.xsd">
    <bean id="exampleBean" class="injection.setter.dao.ExampleBean">
        <property name="beanOne" ref="anotherBean" />
        <property name="beanTwo" ref="yetAnotherBean"/>
        <property name="integerProperty" value="100"/>
    </bean>
    <bean id="anotherBean" class="injection.setter.dao.AnotherBean">
        <constructor-arg value="this is another bean"/>
    </bean>
    <bean id="yetAnotherBean" class="injection.setter.dao.YetAnotherBean">
        <constructor-arg value="this is yet another bean"/>
    </bean>
</beans>